dsd_upsun/__init__.py
dsd_upsun/deploy.py
dsd_upsun/deploy_messages.py
dsd_upsun/platform_deployer.py
dsd_upsun/plugin_config.py
dsd_upsun/utils.py
dsd_upsun/templates/pipenv.platform.app.yaml
dsd_upsun/templates/platform.app.yaml
dsd_upsun/templates/poetry.platform.app.yaml
dsd_upsun/templates/services.yaml
dsd_upsun/templates/settings.py
dsd_upsun-1.2.1.dist-info/licenses/LICENSE
dsd_upsun-1.2.1.dist-info/METADATA
dsd_upsun-1.2.1.dist-info/WHEEL
dsd_upsun-1.2.1.dist-info/top_level.txt
dsd_upsun-1.2.1.dist-info/RECORD
